typeracerScraper_package/__init__.py
typeracerScraper_package/typeracerScraper.py
typeRacerScraper_pkg-0.0.5.dist-info/LICENSE
typeRacerScraper_pkg-0.0.5.dist-info/METADATA
typeRacerScraper_pkg-0.0.5.dist-info/WHEEL
typeRacerScraper_pkg-0.0.5.dist-info/top_level.txt
typeRacerScraper_pkg-0.0.5.dist-info/RECORD
