Metadata-Version: 2.1
Name: typeRacerScraper-pkg
Version: 0.0.5
Summary: Scrapes scores from typeracer given a username.
Home-page: https://github.com/Mohammad-Kheir/TypeRacerScraper
Author: Mohammad Kheir
Author-email: kheir.mirza@gmail.com
License: UNKNOWN
Project-URL: Bug Tracker, https://github.com/Mohammad-Kheir/TypeRacerScraper
Platform: UNKNOWN
Classifier: Programming Language :: Python :: 3
Classifier: License :: OSI Approved :: MIT License
Classifier: Operating System :: OS Independent
Requires-Python: >=3.6
License-File: LICENSE
Requires-Dist: requests
Requires-Dist: beautifulsoup4
Requires-Dist: pandas
